logger4me/__init__.py
logger4me/logger.py
logger4me-0.1.1.dist-info/licenses/LICENSE
logger4me-0.1.1.dist-info/METADATA
logger4me-0.1.1.dist-info/WHEEL
logger4me-0.1.1.dist-info/top_level.txt
logger4me-0.1.1.dist-info/RECORD
