Metadata-Version: 2.4
Name: logger4me
Version: 0.1.1
Summary: Add your description here
Home-page: https://github.com/the0807/logger4me
Author: the0807
Author-email: the0807.eom@gmail.com
Requires-Python: >=3.6
License-File: LICENSE
Requires-Dist: setuptools>=80.9.0
Requires-Dist: twine>=6.2.0
Requires-Dist: wheel>=0.45.1
Dynamic: author
Dynamic: author-email
Dynamic: home-page
Dynamic: license-file
Dynamic: requires-python
